{
  "main": {
    "id": "04cd0f507603731d",
    "type": "split",
    "children": [
      {
        "id": "c4c636a40f9af471",
        "type": "tabs",
        "children": [
          {
            "id": "f3354ab88ada454e",
            "type": "leaf",
            "state": {
              "type": "empty",
              "state": {}
            }
          },
          {
            "id": "be9c496f908b120f",
            "type": "leaf",
            "state": {
              "type": "graph",
              "state": {}
            }
          },
          {
            "id": "f938575893f5a4b0",
            "type": "leaf",
            "state": {
              "type": "markdown",
              "state": {
                "file": "CISA (Certified Information Systems Auditor)/CISA by Hemang Doshi/Domain 2 - Governance and Management of IT/Section 2 Notes.md",
                "mode": "source",
                "source": false
              }
            }
          },
          {
            "id": "6496409af15c57ac",
            "type": "leaf",
            "state": {
              "type": "markdown",
              "state": {
                "file": "Asgard/Orientation.md",
                "mode": "source",
                "source": false
              }
            }
          },
          {
            "id": "e21b65922ef33d46",
            "type": "leaf",
            "state": {
              "type": "empty",
              "state": {}
            }
          }
        ],
        "currentTab": 3
      }
    ],
    "direction": "vertical"
  },
  "left": {
    "id": "4b5ff1fe50f24283",
    "type": "split",
    "children": [
      {
        "id": "1da4cf33569f6f4a",
        "type": "tabs",
        "children": [
          {
            "id": "f76b4701e2f780fb",
            "type": "leaf",
            "state": {
              "type": "file-explorer",
              "state": {
                "sortOrder": "alphabetical"
              }
            }
          },
          {
            "id": "a0cb168607c70a32",
            "type": "leaf",
            "state": {
              "type": "search",
              "state": {
                "query": "",
                "matchingCase": false,
                "explainSearch": false,
                "collapseAll": false,
                "extraContext": false,
                "sortOrder": "alphabetical"
              }
            }
          },
          {
            "id": "6b157737a38fde61",
            "type": "leaf",
            "state": {
              "type": "starred",
              "state": {}
            }
          }
        ]
      }
    ],
    "direction": "horizontal",
    "width": 200
  },
  "right": {
    "id": "3a2fd77bee45c20b",
    "type": "split",
    "children": [
      {
        "id": "7e726f80f9770900",
        "type": "tabs",
        "children": [
          {
            "id": "6d99693bde768994",
            "type": "leaf",
            "state": {
              "type": "backlink",
              "state": {
                "file": "Asgard/Orientation.md",
                "collapseAll": false,
                "extraContext": false,
                "sortOrder": "alphabetical",
                "showSearch": false,
                "searchQuery": "",
                "backlinkCollapsed": false,
                "unlinkedCollapsed": true
              }
            }
          },
          {
            "id": "9992be6892c5b11c",
            "type": "leaf",
            "state": {
              "type": "outgoing-link",
              "state": {
                "file": "Asgard/Orientation.md",
                "linksCollapsed": false,
                "unlinkedCollapsed": true
              }
            }
          },
          {
            "id": "1aca1744626b8841",
            "type": "leaf",
            "state": {
              "type": "tag",
              "state": {
                "sortOrder": "frequency",
                "useHierarchy": true
              }
            }
          },
          {
            "id": "b44deb5b77bf16a8",
            "type": "leaf",
            "state": {
              "type": "outline",
              "state": {
                "file": "Asgard/Orientation.md"
              }
            }
          }
        ]
      }
    ],
    "direction": "horizontal",
    "width": 200,
    "collapsed": true
  },
  "active": "6496409af15c57ac",
  "lastOpenFiles": [
    "Bug Bounty Hunter/HyperText Transfer Protocol (HTTP).md",
    "Appendix.md",
    "CISA (Certified Information Systems Auditor)/CISA by Hemang Doshi/Domain 4/Section 4 Notes.md",
    "CISA (Certified Information Systems Auditor)/CISA by Hemang Doshi/Domain 2 - Governance and Management of IT/Section 2 Notes.md",
    "Python/Cracking the Code.md",
    "Python/Keylogger.md",
    "CISA (Certified Information Systems Auditor)/CISA by Hemang Doshi/Domain 3/Overview.md",
    "CISA (Certified Information Systems Auditor)/CISA by Hemang Doshi/Domain 3/Domain 3 - Exam Notes.md",
    "TryHackMe/Google Dorking (Hacking).md",
    "TryHackMe/Intro to Offensive Security.md"
  ]
}